Workbook

Sheet Assumptions
A1: KESKO CORPORATION - ASSUMPTIONS
A2: Blue cells = editable inputs
B4: 2024A | C4: 2025E | D4: 2026E | E4: 2027E | F4: 2028E | G4: 2029E
A5: REVENUE GROWTH
A6: Grocery Trade Growth | B6: -0.009 | C6: 0.015 | D6: 0.02 | E6: 0.025 | F6: 0.03 | G6: 0.03
A7: Building & Technical Growth | B7: -0.025 | C7: 0.005 | D7: 0.015 | E7: 0.02 | F7: 0.025 | G7: 0.025
A8: Car Trade Growth | B8: -0.05 | C8: -0.02 | D8: 0 | E8: 0.015 | F8: 0.02 | G8: 0.02
A10: SEGMENT MARGINS
A11: Grocery Trade Margin | B11: 0.052 | C11: 0.053 | D11: 0.054 | E11: 0.055 | F11: 0.056 | G11: 0.056
A12: Building & Technical Margin | B12: 0.038 | C12: 0.04 | D12: 0.042 | E12: 0.044 | F12: 0.045 | G12: 0.045
A13: Car Trade Margin | B13: 0.029 | C13: 0.03 | D13: 0.031 | E13: 0.032 | F13: 0.033 | G13: 0.033
A15: OPERATING
A16: SG&A % Revenue | B16: 0.158 | C16: 0.155 | D16: 0.153 | E16: 0.151 | F16: 0.15 | G16: 0.15
A17: D&A % Revenue | B17: 0.035 | C17: 0.035 | D17: 0.034 | E17: 0.034 | F17: 0.033 | G17: 0.033
A18: Tax Rate | B18: 0.2 | C18: 0.2 | D18: 0.2 | E18: 0.2 | F18: 0.2 | G18: 0.2
A19: Interest Rate | B19: 0.045 | C19: 0.045 | D19: 0.043 | E19: 0.041 | F19: 0.04 | G19: 0.04
A21: WORKING CAPITAL
A22: DSO (days) | B22: 21 | C22: 21 | D22: 21 | E22: 20 | F22: 20 | G22: 20
A23: DIO (days) | B23: 33 | C23: 33 | D23: 32 | E23: 32 | F23: 31 | G23: 31
A24: DPO (days) | B24: 38 | C24: 38 | D24: 38 | E24: 39 | F24: 39 | G24: 40
A26: CAPITAL ALLOCATION
A27: CapEx % Revenue | B27: 0.033 | C27: 0.033 | D27: 0.032 | E27: 0.031 | F27: 0.03 | G27: 0.03
A28: Dividend Payout | B28: 0.8 | C28: 0.8 | D28: 0.8 | E28: 0.75 | F28: 0.75 | G28: 0.75

Sheet Income Statement
A1: INCOME STATEMENT (€M)
B3: 2024A | C3: 2025E | D3: 2026E | E3: 2027E | F3: 2028E | G3: 2029E
A4: Revenue | B4: 11857 | C4: =C5+C6+C7 -> 11955.405 | D4: =D5+D6+D7 -> 12152.203 | E4: =E5+E6+E7 -> 12425.034 | F4: =F5+F6+F7 -> 12766.25 | G4: =G5+G6+G7 -> 13116.973
A5: Grocery Trade | B5: 6877 | C5: =B5*(1+Assumptions!C6) -> 6980.155 | D5: =C5*(1+Assumptions!D6) -> 7119.7581 | E5: =D5*(1+Assumptions!E6) -> 7297.7521 | F5: =E5*(1+Assumptions!F6) -> 7516.6846 | G5: =F5*(1+Assumptions!G6) -> 7742.1852
A6: Building & Technical | B6: 3794 | C6: =B6*(1+Assumptions!C7) -> 3812.97 | D6: =C6*(1+Assumptions!D7) -> 3870.1645 | E6: =D6*(1+Assumptions!E7) -> 3947.5678 | F6: =E6*(1+Assumptions!F7) -> 4046.257 | G6: =F6*(1+Assumptions!G7) -> 4147.4135
A7: Car Trade | B7: 1186 | C7: =B7*(1+Assumptions!C8) -> 1162.28 | D7: =C7*(1+Assumptions!D8) -> 1162.28 | E7: =D7*(1+Assumptions!E8) -> 1179.7142 | F7: =E7*(1+Assumptions!F8) -> 1203.3085 | G7: =F7*(1+Assumptions!G8) -> 1227.3747
A8: Revenue Growth | B8: -0.009 | C8: =(C4-B4)/B4 -> 0.0082993169 | D8: =(D4-C4)/C4 -> 0.016460977 | E8: =(E4-D4)/D4 -> 0.022451193 | F8: =(F4-E4)/E4 -> 0.02746198 | G8: =(G4-F4)/F4 -> 0.027472682
A10: Gross Profit | B10: 2404 | C10: =C5*Assumptions!C11+C6*Assumptions!C12+C7*Assumptions!C13 -> 557.33542 | D10: =D5*Assumptions!D11+D6*Assumptions!D12+D7*Assumptions!D13 -> 583.04453 | E10: =E5*Assumptions!E11+E6*Assumptions!E12+E7*Assumptions!E13 -> 612.8202 | F10: =F5*Assumptions!F11+F6*Assumptions!F12+F7*Assumptions!F13 -> 642.72509 | G10: =G5*Assumptions!G11+G6*Assumptions!G12+G7*Assumptions!G13 -> 660.69934
A11: SG&A Expenses | B11: -1466 | C11: =-C4*Assumptions!C16 -> -1853.0878 | D11: =-D4*Assumptions!D16 -> -1859.287 | E11: =-E4*Assumptions!E16 -> -1876.1801 | F11: =-F4*Assumptions!F16 -> -1914.9375 | G11: =-G4*Assumptions!G16 -> -1967.546
A12: Depreciation & Amortization | B12: -412 | C12: =-C4*Assumptions!C17 -> -418.43917 | D12: =-D4*Assumptions!D17 -> -413.17489 | E12: =-E4*Assumptions!E17 -> -422.45116 | F12: =-F4*Assumptions!F17 -> -421.28625 | G12: =-G4*Assumptions!G17 -> -432.86012
A14: Operating Profit (EBIT) | B14: =B10+B11+B12 -> 526 | C14: =C10+C11+C12 -> -1714.1915 | D14: =D10+D11+D12 -> -1689.4174 | E14: =E10+E11+E12 -> -1685.8111 | F14: =F10+F11+F12 -> -1693.4987 | G14: =G10+G11+G12 -> -1739.7068
A15: EBITDA | B15: =B14-B12 -> 938 | C15: =C14-C12 -> -1295.7524 | D15: =D14-D12 -> -1276.2425 | E15: =E14-E12 -> -1263.3599 | F15: =F14-F12 -> -1272.2124 | G15: =G14-G12 -> -1306.8467
A17: Interest Expense | B17: -146 | C17: =-'Balance Sheet'!B26*Assumptions!C19 -> -40.14 | D17: =-'Balance Sheet'!C26*Assumptions!D19 -> 4.644 | E17: =-'Balance Sheet'!D26*Assumptions!E19 -> 4.428 | F17: =-'Balance Sheet'!E26*Assumptions!F19 -> 4.32 | G17: =-'Balance Sheet'!F26*Assumptions!G19 -> 4.32
A18: Profit Before Tax | B18: =B14+B17 -> 380 | C18: =C14+C17 -> -1754.3315 | D18: =D14+D17 -> -1684.7734 | E18: =E14+E17 -> -1681.3831 | F18: =F14+F17 -> -1689.1787 | G18: =G14+G17 -> -1735.3868
A19: Income Tax | B19: -76 | C19: =-C18*Assumptions!C18 -> 350.86631 | D19: =-D18*Assumptions!D18 -> 336.95467 | E19: =-E18*Assumptions!E18 -> 336.27662 | F19: =-F18*Assumptions!F18 -> 337.83574 | G19: =-G18*Assumptions!G18 -> 347.07735
A21: Net Profit | B21: =B18+B19 -> 304 | C21: =C18+C19 -> -1403.4652 | D21: =D18+D19 -> -1347.8187 | E21: =E18+E19 -> -1345.1065 | F21: =F18+F19 -> -1351.343 | G21: =G18+G19 -> -1388.3094

Sheet Balance Sheet
A1: BALANCE SHEET (€M)
B3: 2024A | C3: 2025E | D3: 2026E | E3: 2027E | F3: 2028E | G3: 2029E
A4: ASSETS
A5: Property, Plant & Equipment | B5: 1842 | C5: =B5-'Cash Flow'!C11+'Income Statement'!C12 -> 1818.0892 | D5: =C5-'Cash Flow'!D11+'Income Statement'!D12 -> 1793.7848 | E5: =D5-'Cash Flow'!E11+'Income Statement'!E12 -> 1756.5097 | F5: =E5-'Cash Flow'!F11+'Income Statement'!F12 -> 1718.2109 | G5: =F5-'Cash Flow'!G11+'Income Statement'!G12 -> 1678.86
A6: Other Non-Current Assets | B6: 3213 | C6: 3213 | D6: 3213 | E6: 3213 | F6: 3213 | G6: 3213
A7: Total Non-Current Assets | B7: =B5+B6 -> 5055 | C7: =C5+C6 -> 5031.0892 | D7: =D5+D6 -> 5006.7848 | E7: =E5+E6 -> 4969.5097 | F7: =F5+F6 -> 4931.2109 | G7: =G5+G6 -> 4891.86
A9: Inventories | B9: 1089 | C9: ='Income Statement'!C4*0.8/365*Assumptions!C23 -> 864.7197 | D9: ='Income Statement'!D4*0.8/365*Assumptions!D23 -> 852.31887 | E9: ='Income Statement'!E4*0.8/365*Assumptions!E23 -> 871.45445 | F9: ='Income Statement'!F4*0.8/365*Assumptions!F23 -> 867.40549 | G9: ='Income Statement'!G4*0.8/365*Assumptions!G23 -> 891.23544
A10: Trade Receivables | B10: 687 | C10: ='Income Statement'!C4/365*Assumptions!C22 -> 687.84522 | D10: ='Income Statement'!D4/365*Assumptions!D22 -> 699.16782 | E10: ='Income Statement'!E4/365*Assumptions!E22 -> 680.82379 | F10: ='Income Statement'!F4/365*Assumptions!F22 -> 699.52056 | G10: ='Income Statement'!G4/365*Assumptions!G22 -> 718.73826
A11: Cash & Equivalents | B11: 234 | C11: =B11+'Cash Flow'!C18 -> -37.609318 | D11: =C11+'Cash Flow'!D18 -> -265.3996 | E11: =D11+'Cash Flow'!E18 -> -515.23621 | F11: =E11+'Cash Flow'!F18 -> -800.25405 | G11: =F11+'Cash Flow'!G18 -> -1092.299
A12: Other Current Assets | B12: 156 | C12: 156 | D12: 156 | E12: 156 | F12: 156 | G12: 156
A13: Total Current Assets | B13: =SUM(B9:B12) -> 2166 | C13: =SUM(C9:C12) -> 1670.9556 | D13: =SUM(D9:D12) -> 1442.0871 | E13: =SUM(E9:E12) -> 1193.042 | F13: =SUM(F9:F12) -> 922.67199 | G13: =SUM(G9:G12) -> 673.67471
A15: TOTAL ASSETS | B15: =B7+B13 -> 7221 | C15: =C7+C13 -> 6702.0448 | D15: =D7+D13 -> 6448.8719 | E15: =E7+E13 -> 6162.5517 | F15: =F7+F13 -> 5853.8829 | G15: =G7+G13 -> 5565.5347
A17: EQUITY & LIABILITIES
A18: Share Capital | B18: 197 | C18: 197 | D18: 197 | E18: 197 | F18: 197 | G18: 197
A19: Retained Earnings | B19: 2856 | C19: =B19+'Income Statement'!C21+'Cash Flow'!C15 -> 2575.307 | D19: =C19+'Income Statement'!D21+'Cash Flow'!D15 -> 2305.7432 | E19: =D19+'Income Statement'!E21+'Cash Flow'!E15 -> 1969.4666 | F19: =E19+'Income Statement'!F21+'Cash Flow'!F15 -> 1631.6309 | G19: =F19+'Income Statement'!G21+'Cash Flow'!G15 -> 1284.5535
A20: Other Equity | B20: 523 | C20: 523 | D20: 523 | E20: 523 | F20: 523 | G20: 523
A21: Total Equity | B21: =B18+B19+B20 -> 3576 | C21: =C18+C19+C20 -> 3295.307 | D21: =D18+D19+D20 -> 3025.7432 | E21: =E18+E19+E20 -> 2689.4666 | F21: =F18+F19+F20 -> 2351.6309 | G21: =G18+G19+G20 -> 2004.5535
A23: Lease Obligations | B23: 1598 | C23: 1598 | D23: 1598 | E23: 1598 | F23: 1598 | G23: 1598
A24: Trade Payables | B24: 1234 | C24: ='Income Statement'!C4*0.8/365*Assumptions!C24 -> 995.73784 | D24: ='Income Statement'!D4*0.8/365*Assumptions!D24 -> 1012.1287 | E24: ='Income Statement'!E4*0.8/365*Assumptions!E24 -> 1062.0851 | F24: ='Income Statement'!F4*0.8/365*Assumptions!F24 -> 1091.2521 | G24: ='Income Statement'!G4*0.8/365*Assumptions!G24 -> 1149.9812
A25: Other Liabilities | B25: 921 | C25: 921 | D25: 921 | E25: 921 | F25: 921 | G25: 921
A26: Long-Term Debt (Plug) | B26: 892 | C26: =C15-C21-C23-C24-C25 -> -108 | D26: =D15-D21-D23-D24-D25 -> -108 | E26: =E15-E21-E23-E24-E25 -> -108 | F26: =F15-F21-F23-F24-F25 -> -108 | G26: =G15-G21-G23-G24-G25 -> -108
A28: TOTAL EQUITY & LIABILITIES | B28: =B21+B23+B24+B25+B26 -> 8221 | C28: =C21+C23+C24+C25+C26 -> 6702.0448 | D28: =D21+D23+D24+D25+D26 -> 6448.8719 | E28: =E21+E23+E24+E25+E26 -> 6162.5517 | F28: =F21+F23+F24+F25+F26 -> 5853.8829 | G28: =G21+G23+G24+G25+G26 -> 5565.5347
A30: Balance Check (=0) | B30: =B15-B28 -> -1000 | C30: =C15-C28 -> 0 | D30: =D15-D28 -> 0 | E30: =E15-E28 -> 0 | F30: =F15-F28 -> 0 | G30: =G15-G28 -> 0

Sheet Cash Flow
A1: CASH FLOW STATEMENT (€M)
B3: 2024A | C3: 2025E | D3: 2026E | E3: 2027E | F3: 2028E | G3: 2029E
A4: OPERATING ACTIVITIES
A5: Net Profit | B5: 304 | C5: ='Income Statement'!C21 -> -1403.4652 | D5: ='Income Statement'!D21 -> -1347.8187 | E5: ='Income Statement'!E21 -> -1345.1065 | F5: ='Income Statement'!F21 -> -1351.343 | G5: ='Income Statement'!G21 -> -1388.3094
A6: (+) Depreciation & Amortization | B6: 412 | C6: =-'Income Statement'!C12 -> 418.43917 | D6: =-'Income Statement'!D12 -> 413.17489 | E6: =-'Income Statement'!E12 -> 422.45116 | F6: =-'Income Statement'!F12 -> 421.28625 | G6: =-'Income Statement'!G12 -> 432.86012
A7: (-) Working Capital Changes | B7: -45 | C7: =-('Balance Sheet'!C9-'Balance Sheet'!B9)-('Balance Sheet'!C10-'Balance Sheet'!B10)+('Balance Sheet'!C24-'Balance Sheet'!B24) -> -14.827082 | D7: =-('Balance Sheet'!D9-'Balance Sheet'!C9)-('Balance Sheet'!D10-'Balance Sheet'!C10)+('Balance Sheet'!D24-'Balance Sheet'!C24) -> 17.469047 | E7: =-('Balance Sheet'!E9-'Balance Sheet'!D9)-('Balance Sheet'!E10-'Balance Sheet'!D10)+('Balance Sheet'!E24-'Balance Sheet'!D24) -> 49.16491 | F7: =-('Balance Sheet'!F9-'Balance Sheet'!E9)-('Balance Sheet'!F10-'Balance Sheet'!E10)+('Balance Sheet'!F24-'Balance Sheet'!E24) -> 14.519148 | G7: =-('Balance Sheet'!G9-'Balance Sheet'!F9)-('Balance Sheet'!G10-'Balance Sheet'!F10)+('Balance Sheet'!G24-'Balance Sheet'!F24) -> 15.68149
A8: Cash from Operations | B8: =B5+B6+B7 -> 671 | C8: =C5+C6+C7 -> -999.85314 | D8: =D5+D6+D7 -> -917.17476 | E8: =E5+E6+E7 -> -873.49042 | F8: =F5+F6+F7 -> -915.53755 | G8: =G5+G6+G7 -> -939.76781
A10: INVESTING ACTIVITIES
A11: Capital Expenditure | B11: -387 | C11: =-'Income Statement'!C4*Assumptions!C27 -> -394.52837 | D11: =-'Income Statement'!D4*Assumptions!D27 -> -388.87048 | E11: =-'Income Statement'!E4*Assumptions!E27 -> -385.17606 | F11: =-'Income Statement'!F4*Assumptions!F27 -> -382.9875 | G11: =-'Income Statement'!G4*Assumptions!G27 -> -393.5092
A12: Cash from Investing | B12: =B11 -> -387 | C12: =C11 -> -394.52837 | D12: =D11 -> -388.87048 | E12: =E11 -> -385.17606 | F12: =F11 -> -382.9875 | G12: =G11 -> -393.5092
A14: FINANCING ACTIVITIES
A15: Dividends Paid | B15: -323 | C15: =-'Income Statement'!C21*Assumptions!C28 -> 1122.7722 | D15: =-'Income Statement'!D21*Assumptions!D28 -> 1078.255 | E15: =-'Income Statement'!E21*Assumptions!E28 -> 1008.8299 | F15: =-'Income Statement'!F21*Assumptions!F28 -> 1013.5072 | G15: =-'Income Statement'!G21*Assumptions!G28 -> 1041.2321
A16: Cash from Financing | B16: =B15 -> -323 | C16: =C15 -> 1122.7722 | D16: =D15 -> 1078.255 | E16: =E15 -> 1008.8299 | F16: =F15 -> 1013.5072 | G16: =G15 -> 1041.2321
A18: Net Change in Cash | B18: =B8+B12+B16 -> -39 | C18: =C8+C12+C16 -> -271.60932 | D18: =D8+D12+D16 -> -227.79029 | E18: =E8+E12+E16 -> -249.83661 | F18: =F8+F12+F16 -> -285.01784 | G18: =G8+G12+G16 -> -292.04494
A20: FREE CASH FLOW
A21: Free Cash Flow | B21: =B8+B12 -> 284 | C21: =C8+C12 -> -1394.3815 | D21: =D8+D12 -> -1306.0452 | E21: =E8+E12 -> -1258.6665 | F21: =F8+F12 -> -1298.5251 | G21: =G8+G12 -> -1333.277

Sheet Key Metrics
A1: KEY FINANCIAL METRICS
B3: 2024A | C3: 2025E | D3: 2026E | E3: 2027E | F3: 2028E | G3: 2029E
A4: PROFITABILITY
A5: Operating Margin | B5: ='Income Statement'!B14/'Income Statement'!B4 -> 0.04436198 | C5: ='Income Statement'!C14/'Income Statement'!C4 -> -0.14338214 | D5: ='Income Statement'!D14/'Income Statement'!D4 -> -0.13902149 | E5: ='Income Statement'!E14/'Income Statement'!E4 -> -0.13567859 | F5: ='Income Statement'!F14/'Income Statement'!F4 -> -0.13265436 | G5: ='Income Statement'!G14/'Income Statement'!G4 -> -0.1326302
A6: Net Profit Margin | B6: ='Income Statement'!B21/'Income Statement'!B4 -> 0.025638863 | C6: ='Income Statement'!C21/'Income Statement'!C4 -> -0.11739169 | D6: ='Income Statement'!D21/'Income Statement'!D4 -> -0.11091147 | E6: ='Income Statement'!E21/'Income Statement'!E4 -> -0.10825777 | F6: ='Income Statement'!F21/'Income Statement'!F4 -> -0.10585277 | G6: ='Income Statement'!G21/'Income Statement'!G4 -> -0.10584068
A8: RETURNS
A9: Return on Equity (ROE) | B9: ='Income Statement'!B21/'Balance Sheet'!B21 -> 0.085011186 | C9: ='Income Statement'!C21/'Balance Sheet'!C21 -> -0.42589818 | D9: ='Income Statement'!D21/'Balance Sheet'!D21 -> -0.44545046 | E9: ='Income Statement'!E21/'Balance Sheet'!E21 -> -0.50013876 | F9: ='Income Statement'!F21/'Balance Sheet'!F21 -> -0.57464076 | G9: ='Income Statement'!G21/'Balance Sheet'!G21 -> -0.69257788
A10: Return on Assets (ROA) | B10: ='Income Statement'!B21/'Balance Sheet'!B15 -> 0.042099432 | C10: ='Income Statement'!C21/'Balance Sheet'!C15 -> -0.20940851 | D10: ='Income Statement'!D21/'Balance Sheet'!D15 -> -0.20900069 | E10: ='Income Statement'!E21/'Balance Sheet'!E15 -> -0.21827103 | F10: ='Income Statement'!F21/'Balance Sheet'!F15 -> -0.23084557 | G10: ='Income Statement'!G21/'Balance Sheet'!G15 -> -0.24944762
A12: LEVERAGE
A13: Net Debt / EBITDA | B13: =('Balance Sheet'!B23+'Balance Sheet'!B26-'Balance Sheet'!B11)/'Income Statement'!B15 -> 2.4051173 | C13: =('Balance Sheet'!C23+'Balance Sheet'!C26-'Balance Sheet'!C11)/'Income Statement'!C15 -> -1.1789362 | D13: =('Balance Sheet'!D23+'Balance Sheet'!D26-'Balance Sheet'!D11)/'Income Statement'!D15 -> -1.3754436 | E13: =('Balance Sheet'!E23+'Balance Sheet'!E26-'Balance Sheet'!E11)/'Income Statement'!E15 -> -1.5872248 | F13: =('Balance Sheet'!F23+'Balance Sheet'!F26-'Balance Sheet'!F11)/'Income Statement'!F15 -> -1.8002135 | G13: =('Balance Sheet'!G23+'Balance Sheet'!G26-'Balance Sheet'!G11)/'Income Statement'!G15 -> -1.9759771
A14: Debt / Equity | B14: =('Balance Sheet'!B23+'Balance Sheet'!B26)/'Balance Sheet'!B21 -> 0.69630872 | C14: =('Balance Sheet'!C23+'Balance Sheet'!C26)/'Balance Sheet'!C21 -> 0.45215818 | D14: =('Balance Sheet'!D23+'Balance Sheet'!D26)/'Balance Sheet'!D21 -> 0.492441 | E14: =('Balance Sheet'!E23+'Balance Sheet'!E26)/'Balance Sheet'!E21 -> 0.5540132 | F14: =('Balance Sheet'!F23+'Balance Sheet'!F26)/'Balance Sheet'!F21 -> 0.63360284 | G14: =('Balance Sheet'!G23+'Balance Sheet'!G26)/'Balance Sheet'!G21 -> 0.74330767
A16: CASH
A17: Free Cash Flow (€M) | B17: ='Cash Flow'!B21 -> 284 | C17: ='Cash Flow'!C21 -> -1394.3815 | D17: ='Cash Flow'!D21 -> -1306.0452 | E17: ='Cash Flow'!E21 -> -1258.6665 | F17: ='Cash Flow'!F21 -> -1298.5251 | G17: ='Cash Flow'!G21 -> -1333.277
A18: Revenue Growth | B18: ='Income Statement'!B8 -> -0.009 | C18: ='Income Statement'!C8 -> 0.0082993169 | D18: ='Income Statement'!D8 -> 0.016460977 | E18: ='Income Statement'!E8 -> 0.022451193 | F18: ='Income Statement'!F8 -> 0.02746198 | G18: ='Income Statement'!G8 -> 0.027472682
